{"cameraMode":{"drawMode":0,"name":"Shaded","section":"Shading Mode"},"sceneLighting":true,"audioPlay":false,"sceneViewState":{"m_AlwaysRefresh":false,"showFog":true,"showSkybox":true,"showFlares":true,"showImageEffects":true,"showParticleSystems":true,"showVisualEffectGraphs":true,"m_FxEnabled":true},"in2DMode":false,"pivot":{"x":-321.4274597167969,"y":1.8800640106201172,"z":-13.820329666137696},"rotation":{"x":-0.15583617985248567,"y":0.038847945630550387,"z":-0.00662045506760478,"w":-0.9871610403060913},"size":11.573629379272461,"orthographic":false}